gisweb_ads/__init__.py
gisweb_ads/ads.py
gisweb_ads/schema.py
gisweb_ads/soap_attachments.py
gisweb_ads/templates/result.xml
gisweb_ads/templates/segnatura.xml
gisweb_ads/templates/segnatura_e.xml
gisweb_ads/templates/segnatura_ok.xml
gisweb_ads-0.5.dist-info/LICENSE
gisweb_ads-0.5.dist-info/METADATA
gisweb_ads-0.5.dist-info/WHEEL
gisweb_ads-0.5.dist-info/RECORD
